eexp_engine/__init__.py
eexp_engine/client.py
eexp_engine/config.py
eexp_engine/error_logger.py
eexp_engine/exceptions.py
eexp_engine/experiment_queue.py
eexp_engine/runner.py
eexp_engine/data_abstraction_layer/data_abstraction_api.py
eexp_engine/executionware/kubeflow_helper.py
eexp_engine/executionware/kubeflow_runner.py
eexp_engine/executionware/kubeflow_utils.py
eexp_engine/executionware/local_runner.py
eexp_engine/executionware/proactive_helper.py
eexp_engine/executionware/proactive_runner.py
eexp_engine/executionware/default_task_requirements/task_requirements.txt
eexp_engine/executionware/scripts/check_node_source_name.groovy
eexp_engine/executionware/scripts/cuda_node_selection.groovy
eexp_engine/executionware/scripts/cuda_node_selection.py
eexp_engine/executionware/scripts/fork_env.groovy
eexp_engine/executionware/scripts/fork_env.py
eexp_engine/executionware/scripts/fork_env2.py
eexp_engine/executionware/scripts/fork_env3.py
eexp_engine/executionware/scripts/fork_env_cntk_gpu.py
eexp_engine/executionware/scripts/fork_env_cuda.py
eexp_engine/executionware/scripts/fork_env_cuda_old.py
eexp_engine/executionware/scripts/print_python_env.py
eexp_engine/executionware/scripts/selection_script.py
eexp_engine/executionware/scripts/task_prescript.py
eexp_engine/executionware/scripts/user_interaction/postscript.py
eexp_engine/executionware/scripts/user_interaction/prescript.py
eexp_engine/executionware/scripts/user_interaction/user_interaction_requirements.txt
eexp_engine/functions/execution.py
eexp_engine/functions/parsing.py
eexp_engine/grammar/task_grammar.tx
eexp_engine/grammar/workflow_grammar.tx
eexp_engine/models/dataset.py
eexp_engine/models/experiment.py
eexp_engine/models/metric.py
eexp_engine/models/task.py
eexp_engine/models/workflow.py
eexp_engine-1.0.3.dist-info/licenses/LICENCE
eexp_engine-1.0.3.dist-info/METADATA
eexp_engine-1.0.3.dist-info/WHEEL
eexp_engine-1.0.3.dist-info/entry_points.txt
eexp_engine-1.0.3.dist-info/top_level.txt
eexp_engine-1.0.3.dist-info/RECORD
