Metadata-Version: 2.4
Name: eexp_engine
Version: 1.0.3
Summary: A command-line version of the experimentation engine of the ExtremeXP project
Author-email: "Ilias Gerostathopoulos, Konstantinos Kozanis, Keerthiga Rajenthiram" <iliasger@gmail.com>
Project-URL: Homepage, https://github.com/extremexp-HORIZON/extremexp-experimentation-engine
Project-URL: Issues, https://github.com/extremexp-HORIZON/extremexp-experimentation-engine/issues
Classifier: Programming Language :: Python :: 3
Classifier: License :: OSI Approved :: Apache Software License
Classifier: Operating System :: OS Independent
Requires-Python: >=3.8
License-File: LICENCE
Requires-Dist: eexp_engine_utils
Requires-Dist: textX>=4.0.1
Requires-Dist: proactive==14.2.0.2505080030.dev0
Requires-Dist: kfp>=2.14.6
Requires-Dist: kfp-kubernetes>=2.14.6
Requires-Dist: minio>=7.2.18
Requires-Dist: InquirerPy
Requires-Dist: rich
Dynamic: license-file
